mishelpers/__init__.py
mishelpers/operaciones.py
mishelpers/traductor.py
mishelpers-1.0.0.dist-info/METADATA
mishelpers-1.0.0.dist-info/WHEEL
mishelpers-1.0.0.dist-info/top_level.txt
mishelpers-1.0.0.dist-info/RECORD
