Metadata-Version: 2.1
Name: mishelpers
Version: 1.0.0
Summary: Un paquete con helpers
Author: Ángel Villalba
Author-email: angelisco92@gmail.com
